{"readiumJsViewer":{"sha":"b3200618cd9e1543292fa9a94b63121ee9d0c18e","clean":false,"version":"0.20.0-alpha","chromeVersion":"2.20.0-alpha","tag":"0.20.0-80-gb320061","branch":"feature/pluginsX","release":false,"timestamp":1432939812249},"readiumJs":{"sha":"6e02a23e5dd6b205ab44a8b88cf87cbb2f9720c3","clean":true,"version":"0.20.0-alpha","tag":"0.17-120-g6e02a23","branch":"feature/pluginsX","release":false,"timestamp":1432939812639},"readiumSharedJs":{"sha":"c9ff8077f8eb8eb19de46b023d1352129fdac2f7","clean":true,"version":"0.20.0-alpha","tag":"0.16-147-gc9ff807","branch":"feature/pluginsX","release":false,"timestamp":1432939812999},"readiumCfiJs":{"sha":"ec276f8ff27b958fd62b15c1b77be12dd7ae519c","clean":true,"version":"0.20.0-alpha","tag":"0.1.4-114-gec276f8","branch":"feature/plugins","release":false,"timestamp":1432939814477}}